odoo/addons/hr_employee_service_contract/README.rst
odoo/addons/hr_employee_service_contract/__init__.py
odoo/addons/hr_employee_service_contract/__manifest__.py
odoo/addons/hr_employee_service_contract/i18n/de.po
odoo/addons/hr_employee_service_contract/i18n/es.po
odoo/addons/hr_employee_service_contract/i18n/es_AR.po
odoo/addons/hr_employee_service_contract/i18n/fr.po
odoo/addons/hr_employee_service_contract/i18n/hr_employee_service_contract.pot
odoo/addons/hr_employee_service_contract/i18n/it.po
odoo/addons/hr_employee_service_contract/models/__init__.py
odoo/addons/hr_employee_service_contract/models/hr_employee.py
odoo/addons/hr_employee_service_contract/readme/CONTRIBUTORS.rst
odoo/addons/hr_employee_service_contract/readme/DESCRIPTION.rst
odoo/addons/hr_employee_service_contract/static/description/icon.png
odoo/addons/hr_employee_service_contract/static/description/index.html
odoo/addons/hr_employee_service_contract/tests/__init__.py
odoo/addons/hr_employee_service_contract/tests/test_hr_employee_service.py
odoo14_addon_hr_employee_service_contract-14.0.1.0.1.dev10.dist-info/METADATA
odoo14_addon_hr_employee_service_contract-14.0.1.0.1.dev10.dist-info/WHEEL
odoo14_addon_hr_employee_service_contract-14.0.1.0.1.dev10.dist-info/top_level.txt
odoo14_addon_hr_employee_service_contract-14.0.1.0.1.dev10.dist-info/RECORD
